woj/__init__.py
woj/api_client.py
woj/api_response.py
woj/configuration.py
woj/exceptions.py
woj/py.typed
woj/rest.py
woj/api/__init__.py
woj/api/auth_api.py
woj/api/default_api.py
woj/api/problem_api.py
woj/api/submission_api.py
woj/models/__init__.py
woj/models/api_auth_get200_response.py
woj/models/api_auth_send_post200_response.py
woj/models/api_auth_send_post400_response.py
woj/models/api_auth_send_post_request.py
woj/models/api_me_get200_response.py
woj/models/api_problem_get200_response.py
woj/models/api_problem_get200_response_problems_inner.py
woj/models/api_problem_id_get200_response.py
woj/models/api_problem_id_get200_response_problem.py
woj/models/api_problem_id_get200_response_problem_policy_inner.py
woj/models/api_problem_id_get200_response_problem_testcase_inner.py
woj/models/api_submission_get200_response.py
woj/models/api_submission_get200_response_submissions_inner.py
woj/models/api_submission_id_get200_response.py
woj/models/api_submission_id_get200_response_submission.py
woj/models/api_submission_post200_response.py
woj/models/api_submission_post_request.py
woj/models/api_sys_get200_response.py
woj/models/api_sys_get200_response_cfg.py
woj/models/api_sys_get200_response_stat.py
woj-0.0.1.dist-info/METADATA
woj-0.0.1.dist-info/WHEEL
woj-0.0.1.dist-info/top_level.txt
woj-0.0.1.dist-info/RECORD
