Metadata-Version: 2.1
Name: woj
Version: 0.0.1
Summary: WASM OJ Wonderland API
Home-page: 
Author: Jacob Lin
Author-email: jacob@csie.cool
License: MIT
Keywords: OpenAPI,OpenAPI-Generator,WASM OJ Wonderland API
Platform: UNKNOWN
Requires-Dist: urllib3 (<2.1.0,>=1.25.3)
Requires-Dist: python-dateutil
Requires-Dist: pydantic (<2,>=1.10.5)
Requires-Dist: aenum
